lab5_back-end/RTL/mul.v
module mul (CLK, RESETn, a, b, y);
	parameter bw = 16;
	
	input [bw-1:0] a, b;
	input CLK;
	input RESETn;
	output [2*bw-1:0] y;
	
	reg [bw-1:0] a_pipe [bw-1:0];
	reg [bw-1:0] b_pipe [bw-1:0];
	reg [2*bw-1:0] partials [bw-1:0];
	
	genvar i, j;
	for(i=0; i<bw; i=i+1) begin : gen1
		always@(posedge CLK) begin
			if(!RESETn) begin
				a_pipe[i] <= 0;
				b_pipe[i] <= 0;
				partials[i] <= 0;
			end
			else begin
				if(i==0) begin
					a_pipe[i] <= a;
					b_pipe[i] <= b;
					partials[i] <=(a_pipe[i][i] ? b_pipe[i] << i : 0);
				end
				else begin
					a_pipe[i] <= a_pipe[i-1];
					b_pipe[i] <= b_pipe[i-1];
					partials[i] <=(a_pipe[i][i] ? b_pipe[i] << i : 0) + partials[i-1];
				end				
			end
		end
	end
	
	assign y = partials[bw-1];

endmodule

lab5_back-end/RTL/TOP.v
`timescale 1ns / 1ps

module TOP(CLK, RESETn, a, b, y);
	parameter bw = 16;
	
	input CLK, RESETn;
	input [bw-1:0] a, b;
	output [2*bw-1:0]y;	

	mul #(.bw(bw))  mul(.CLK(CLK), .RESETn(RESETn), .a(a), .b(b), .y(y));

endmodule

lab5_back-end/SIM/TESTBENCH/TB_TOP.v
`timescale 1ns / 1ps

module TB_TOP;
	
	parameter bw=16;
	// Inputs
	reg CLK;
	reg RESETn;
	reg [bw-1:0] a;
	reg [bw-1:0] b;

	// Outputs
	wire [2*bw-1:0] y;

	// Instantiate the Unit Under Test (UUT)
	TOP uut (
		.CLK(CLK), 
		.RESETn(RESETn),
		.a(a), 
		.b(b),
		.y(y)
	);

	initial begin
		// Initialize Inputs
		CLK = 0;
		RESETn = 0;
		a = 0;
		b = 0;

		// Wait 100 ns for global reset to finish
		#100;
        
		// Add stimulus here
		RESETn = 1;

		#10000;
		$finish;
		
	end
	
	always #20 a = a + 1;
	always #20 b = b + 2;
	initial begin
		forever #10 CLK = ~CLK;
	end
endmodule

lab5_back-end/SIM/FUNCTION/TOP.vcd
$date
	Mon Nov 14 18:08:42 2022

$end
$version
	Chronologic Simulation VCS Release M-2017.03-SP2
$end
$timescale
	1ps
$end
$scope module TB_TOP $end
$var reg 1 ! CLK $end
$var reg 1 " RESETn $end
$var reg 4 # a [3:0] $end
$var reg 4 $ b [3:0] $end
$var wire 8 % y [7:0] $end
$scope module uut $end
$var wire 1 & CLK $end
$var wire 1 ' RESETn $end
$var wire 4 ( a [3:0] $end
$var wire 4 ) b [3:0] $end
$var wire 8 % y [7:0] $end
$scope module mul $end
$var wire 4 ( a [3:0] $end
$var wire 4 ) b [3:0] $end
$var wire 1 & CLK $end
$var wire 1 ' RESETn $end
$var wire 8 % y [7:0] $end
$upscope $end
$upscope $end
$upscope $end
$enddefinitions $end
$dumpvars
0!
b0000 )
0"
b0000 $
b0000 (
bxxxxxxxx %
b0000 #
0&
0'
$end
#10000
1&
1!
b00000000 %
#20000
0!
0&
b0010 )
b0001 #
b0001 (
b0010 $
#30000
1!
1&
#40000
0!
0&
b0100 $
b0010 (
b0010 #
b0100 )
#50000
1&
1!
#60000
0&
0!
b0110 )
b0011 #
b0011 (
b0110 $
#70000
1!
1&
#80000
0!
0&
b1000 $
b0100 (
b0100 #
b1000 )
#90000
1&
1!
#100000
0&
0!
b1010 )
b0101 #
1"
b0101 (
1'
b1010 $
#110000
1&
1!
#120000
0&
0!
b1100 $
b1100 )
b0110 (
b0110 #
#130000
1!
1&
#140000
0!
0&
b0111 #
b0111 (
b1110 )
b1110 $
#150000
1&
1!
#160000
0&
0!
b0000 $
b0000 )
b1000 (
b1000 #
#170000
1!
1&
#180000
0!
0&
b1001 #
b1001 (
b0010 )
b0010 $
#190000
1&
1!
b00110010 %
#200000
0!
0&
b0100 )
b0100 $
b1010 (
b1010 #
#210000
1&
b01001000 %
1!
#220000
0&
0!
b1011 (
b1011 #
b0110 $
b0110 )
#230000
1!
b01100010 %
1&
#240000
0!
0&
b1000 $
b1000 )
b1100 #
b1100 (
#250000
1&
b00000000 %
1!
#260000
0&
0!
b1101 #
b1101 (
b1010 )
b1010 $
#270000
1!
b00010010 %
1&
#280000
0!
0&
b1100 )
b1100 $
b1110 (
b1110 #
#290000
1&
b00101000 %
1!
#300000
0&
0!
b1111 (
b1111 #
b1110 $
b1110 )
#310000
1!
b01000010 %
1&
#320000
0!
0&
b0000 $
b0000 )
b0000 #
b0000 (
#330000
1&
b01100000 %
1!
#340000
0&
0!
b0001 #
b0001 (
b0010 )
b0010 $
#350000
1!
b10000010 %
1&
#360000
0!
0&
b0100 )
b0100 $
b0010 (
b0010 #
#370000
1&
b10101000 %
1!
#380000
0&
0!
b0011 (
b0011 #
b0110 $
b0110 )
#390000
1!
b11010010 %
1&
#400000
0!
0&
b1000 $
b1000 )
b0100 #
b0100 (
#410000
1&
b00000000 %
1!
#420000
0&
0!
b0101 #
b0101 (
b1010 )
b1010 $
#430000
1!
b00000010 %
1&
#440000
0!
0&
b1100 )
b1100 $
b0110 (
b0110 #
#450000
1&
b00001000 %
1!
#460000
0&
0!
b0111 (
b0111 #
b1110 $
b1110 )
#470000
1!
b00010010 %
1&
#480000
0!
0&
b0000 $
b0000 )
b1000 #
b1000 (
#490000
1&
b00100000 %
1!
#500000
0&
0!
b1001 #
b1001 (
b0010 )
b0010 $
#510000
1!
b00110010 %
1&
#520000
0!
0&
b0100 )
b0100 $
b1010 (
b1010 #
#530000
1&
b01001000 %
1!
#540000
0&
0!
b1011 (
b1011 #
b0110 $
b0110 )
#550000
1!
b01100010 %
1&
#560000
0!
0&
b1000 $
b1000 )
b1100 #
b1100 (
#570000
1&
b00000000 %
1!
#580000
0&
0!
b1101 #
b1101 (
b1010 )
b1010 $
#590000
1!
b00010010 %
1&
#600000
0!
0&
b1100 )
b1100 $
b1110 (
b1110 #
#610000
1&
b00101000 %
1!
#620000
0&
0!
b1111 (
b1111 #
b1110 $
b1110 )
#630000
1!
b01000010 %
1&
#640000
0!
0&
b0000 $
b0000 )
b0000 #
b0000 (
#650000
1&
b01100000 %
1!
#660000
0&
0!
b0001 #
b0001 (
b0010 )
b0010 $
#670000
1!
b10000010 %
1&
#680000
0!
0&
b0100 )
b0100 $
b0010 (
b0010 #
#690000
1&
b10101000 %
1!
#700000
0&
0!
b0011 (
b0011 #
b0110 $
b0110 )
#710000
1!
b11010010 %
1&
#720000
0!
0&
b1000 $
b1000 )
b0100 #
b0100 (
#730000
1&
b00000000 %
1!
#740000
0&
0!
b0101 #
b0101 (
b1010 )
b1010 $
#750000
1!
b00000010 %
1&
#760000
0!
0&
b1100 )
b1100 $
b0110 (
b0110 #
#770000
1&
b00001000 %
1!
#780000
0&
0!
b0111 (
b0111 #
b1110 $
b1110 )
#790000
1!
b00010010 %
1&
#800000
0!
0&
b0000 $
b0000 )
b1000 #
b1000 (
#810000
1&
b00100000 %
1!
#820000
0&
0!
b1001 #
b1001 (
b0010 )
b0010 $
#830000
1!
b00110010 %
1&
#840000
0!
0&
b0100 )
b0100 $
b1010 (
b1010 #
#850000
1&
b01001000 %
1!
#860000
0&
0!
b1011 (
b1011 #
b0110 $
b0110 )
#870000
1!
b01100010 %
1&
#880000
0!
0&
b1000 $
b1000 )
b1100 #
b1100 (
#890000
1&
b00000000 %
1!
#900000
0&
0!
b1101 #
b1101 (
b1010 )
b1010 $
#910000
1!
b00010010 %
1&
#920000
0!
0&
b1100 )
b1100 $
b1110 (
b1110 #
#930000
1&
b00101000 %
1!
#940000
0&
0!
b1111 (
b1111 #
b1110 $
b1110 )
#950000
1!
b01000010 %
1&
#960000
0!
0&
b0000 $
b0000 )
b0000 #
b0000 (
#970000
1&
b01100000 %
1!
#980000
0&
0!
b0001 #
b0001 (
b0010 )
b0010 $
#990000
1!
b10000010 %
1&
#1000000
0!
0&
b0100 )
b0100 $
b0010 (
b0010 #
#1010000
1&
b10101000 %
1!
#1020000
0&
0!
b0011 (
b0011 #
b0110 $
b0110 )
#1030000
1!
b11010010 %
1&
#1040000
0!
0&
b1000 $
b1000 )
b0100 #
b0100 (
#1050000
1&
b00000000 %
1!
#1060000
0&
0!
b0101 #
b0101 (
b1010 )
b1010 $
#1070000
1!
b00000010 %
1&
#1080000
0!
0&
b1100 )
b1100 $
b0110 (
b0110 #
#1090000
1&
b00001000 %
1!
#1100000
0&
0!
b0111 (
b0111 #
b1110 $
b1110 )
#1110000
1!
b00010010 %
1&
#1120000
0!
0&
b0000 $
b0000 )
b1000 #
b1000 (
#1130000
1&
b00100000 %
1!
#1140000
0&
0!
b1001 #
b1001 (
b0010 )
b0010 $
#1150000
1!
b00110010 %
1&
#1160000
0!
0&
b0100 )
b0100 $
b1010 (
b1010 #
#1170000
1&
b01001000 %
1!
#1180000
0&
0!
b1011 (
b1011 #
b0110 $
b0110 )
#1190000
1!
b01100010 %
1&
#1200000
0!
0&
b1000 $
b1000 )
b1100 #
b1100 (
#1210000
1&
b00000000 %
1!
#1220000
0&
0!
b1101 #
b1101 (
b1010 )
b1010 $
#1230000
1!
b00010010 %
1&
#1240000
0!
0&
b1100 )
b1100 $
b1110 (
b1110 #
#1250000
1&
b00101000 %
1!
#1260000
0&
0!
b1111 (
b1111 #
b1110 $
b1110 )
#1270000
1!
b01000010 %
1&
#1280000
0!
0&
b0000 $
b0000 )
b0000 #
b0000 (
#1290000
1&
b01100000 %
1!
#1300000
0&
0!
b0001 #
b0001 (
b0010 )
b0010 $
#1310000
1!
b10000010 %
1&
#1320000
0!
0&
b0100 )
b0100 $
b0010 (
b0010 #
#1330000
1&
b10101000 %
1!
#1340000
0&
0!
b0011 (
b0011 #
b0110 $
b0110 )
#1350000
1!
b11010010 %
1&
#1360000
0!
0&
b1000 $
b1000 )
b0100 #
b0100 (
#1370000
1&
b00000000 %
1!
#1380000
0&
0!
b0101 #
b0101 (
b1010 )
b1010 $
#1390000
1!
b00000010 %
1&
#1400000
0!
0&
b1100 )
b1100 $
b0110 (
b0110 #
#1410000
1&
b00001000 %
1!
#1420000
0&
0!
b0111 (
b0111 #
b1110 $
b1110 )
#1430000
1!
b00010010 %
1&
#1440000
0!
0&
b0000 $
b0000 )
b1000 #
b1000 (
#1450000
1&
b00100000 %
1!
#1460000
0&
0!
b1001 #
b1001 (
b0010 )
b0010 $
#1470000
1!
b00110010 %
1&
#1480000
0!
0&
b0100 )
b0100 $
b1010 (
b1010 #
#1490000
1&
b01001000 %
1!
#1500000
0&
0!
b1011 (
b1011 #
b0110 $
b0110 )
#1510000
1!
b01100010 %
1&
#1520000
0!
0&
b1000 $
b1000 )
b1100 #
b1100 (
#1530000
1&
b00000000 %
1!
#1540000
0&
0!
b1101 #
b1101 (
b1010 )
b1010 $
#1550000
1!
b00010010 %
1&
#1560000
0!
0&
b1100 )
b1100 $
b1110 (
b1110 #
#1570000
1&
b00101000 %
1!
#1580000
0&
0!
b1111 (
b1111 #
b1110 $
b1110 )
#1590000
1!
b01000010 %
1&
#1600000
0!
0&
b0000 $
b0000 )
b0000 #
b0000 (
#1610000
1&
b01100000 %
1!
#1620000
0&
0!
b0001 #
b0001 (
b0010 )
b0010 $
#1630000
1!
b10000010 %
1&
#1640000
0!
0&
b0100 )
b0100 $
b0010 (
b0010 #
#1650000
1&
b10101000 %
1!
#1660000
0&
0!
b0011 (
b0011 #
b0110 $
b0110 )
#1670000
1!
b11010010 %
1&
#1680000
0!
0&
b1000 $
b1000 )
b0100 #
b0100 (
#1690000
1&
b00000000 %
1!
#1700000
0&
0!
b0101 #
b0101 (
b1010 )
b1010 $
#1710000
1!
b00000010 %
1&
#1720000
0!
0&
b1100 )
b1100 $
b0110 (
b0110 #
#1730000
1&
b00001000 %
1!
#1740000
0&
0!
b0111 (
b0111 #
b1110 $
b1110 )
#1750000
1!
b00010010 %
1&
#1760000
0!
0&
b0000 $
b0000 )
b1000 #
b1000 (
#1770000
1&
b00100000 %
1!
#1780000
0&
0!
b1001 #
b1001 (
b0010 )
b0010 $
#1790000
1!
b00110010 %
1&
#1800000
0!
0&
b0100 )
b0100 $
b1010 (
b1010 #
#1810000
1&
b01001000 %
1!
#1820000
0&
0!
b1011 (
b1011 #
b0110 $
b0110 )
#1830000
1!
b01100010 %
1&
#1840000
0!
0&
b1000 $
b1000 )
b1100 #
b1100 (
#1850000
1&
b00000000 %
1!
#1860000
0&
0!
b1101 #
b1101 (
b1010 )
b1010 $
#1870000
1!
b00010010 %
1&
#1880000
0!
0&
b1100 )
b1100 $
b1110 (
b1110 #
#1890000
1&
b00101000 %
1!
#1900000
0&
0!
b1111 (
b1111 #
b1110 $
b1110 )
#1910000
1!
b01000010 %
1&
#1920000
0!
0&
b0000 $
b0000 )
b0000 #
b0000 (
#1930000
1&
b01100000 %
1!
#1940000
0&
0!
b0001 #
b0001 (
b0010 )
b0010 $
#1950000
1!
b10000010 %
1&
#1960000
0!
0&
b0100 )
b0100 $
b0010 (
b0010 #
#1970000
1&
b10101000 %
1!
#1980000
0&
0!
b0011 (
b0011 #
b0110 $
b0110 )
#1990000
1!
b11010010 %
1&
#2000000
0!
0&
b1000 $
b1000 )
b0100 #
b0100 (
#2010000
1&
b00000000 %
1!
#2020000
0&
0!
b0101 #
b0101 (
b1010 )
b1010 $
#2030000
1!
b00000010 %
1&
#2040000
0!
0&
b1100 )
b1100 $
b0110 (
b0110 #
#2050000
1&
b00001000 %
1!
#2060000
0&
0!
b0111 (
b0111 #
b1110 $
b1110 )
#2070000
1!
b00010010 %
1&
#2080000
0!
0&
b0000 $
b0000 )
b1000 #
b1000 (
#2090000
1&
b00100000 %
1!
#2100000
0&
0!
b1001 #
b1001 (
b0010 )
b0010 $
#2110000
1!
b00110010 %
1&
#2120000
0!
0&
b0100 )
b0100 $
b1010 (
b1010 #
#2130000
1&
b01001000 %
1!
#2140000
0&
0!
b1011 (
b1011 #
b0110 $
b0110 )
#2150000
1!
b01100010 %
1&
#2160000
0!
0&
b1000 $
b1000 )
b1100 #
b1100 (
#2170000
1&
b00000000 %
1!
#2180000
0&
0!
b1101 #
b1101 (
b1010 )
b1010 $
#2190000
1!
b00010010 %
1&
#2200000
0!
0&
b1100 )
b1100 $
b1110 (
b1110 #
#2210000
1&
b00101000 %
1!
#2220000
0&
0!
b1111 (
b1111 #
b1110 $
b1110 )
#2230000
1!
b01000010 %
1&
#2240000
0!
0&
b0000 $
b0000 )
b0000 #
b0000 (
#2250000
1&
b01100000 %
1!
#2260000
0&
0!
b0001 #
b0001 (
b0010 )
b0010 $
#2270000
1!
b10000010 %
1&
#2280000
0!
0&
b0100 )
b0100 $
b0010 (
b0010 #
#2290000
1&
b10101000 %
1!
#2300000
0&
0!
b0011 (
b0011 #
b0110 $
b0110 )
#2310000
1!
b11010010 %
1&
#2320000
0!
0&
b1000 $
b1000 )
b0100 #
b0100 (
#2330000
1&
b00000000 %
1!
#2340000
0&
0!
b0101 #
b0101 (
b1010 )
b1010 $
#2350000
1!
b00000010 %
1&
#2360000
0!
0&
b1100 )
b1100 $
b0110 (
b0110 #
#2370000
1&
b00001000 %
1!
#2380000
0&
0!
b0111 (
b0111 #
b1110 $
b1110 )
#2390000
1!
b00010010 %
1&
#2400000
0!
0&
b0000 $
b0000 )
b1000 #
b1000 (
#2410000
1&
b00100000 %
1!
#2420000
0&
0!
b1001 #
b1001 (
b0010 )
b0010 $
#2430000
1!
b00110010 %
1&
#2440000
0!
0&
b0100 )
b0100 $
b1010 (
b1010 #
#2450000
1&
b01001000 %
1!
#2460000
0&
0!
b1011 (
b1011 #
b0110 $
b0110 )
#2470000
1!
b01100010 %
1&
#2480000
0!
0&
b1000 $
b1000 )
b1100 #
b1100 (
#2490000
1&
b00000000 %
1!
#2500000
0&
0!
b1101 #
b1101 (
b1010 )
b1010 $
#2510000
1!
b00010010 %
1&
#2520000
0!
0&
b1100 )
b1100 $
b1110 (
b1110 #
#2530000
1&
b00101000 %
1!
#2540000
0&
0!
b1111 (
b1111 #
b1110 $
b1110 )
#2550000
1!
b01000010 %
1&
#2560000
0!
0&
b0000 $
b0000 )
b0000 #
b0000 (
#2570000
1&
b01100000 %
1!
#2580000
0&
0!
b0001 #
b0001 (
b0010 )
b0010 $
#2590000
1!
b10000010 %
1&
#2600000
0!
0&
b0100 )
b0100 $
b0010 (
b0010 #
#2610000
1&
b10101000 %
1!
#2620000
0&
0!
b0011 (
b0011 #
b0110 $
b0110 )
#2630000
1!
b11010010 %
1&
#2640000
0!
0&
b1000 $
b1000 )
b0100 #
b0100 (
#2650000
1&
b00000000 %
1!
#2660000
0&
0!
b0101 #
b0101 (
b1010 )
b1010 $
#2670000
1!
b00000010 %
1&
#2680000
0!
0&
b1100 )
b1100 $
b0110 (
b0110 #
#2690000
1&
b00001000 %
1!
#2700000
0&
0!
b0111 (
b0111 #
b1110 $
b1110 )
#2710000
1!
b00010010 %
1&
#2720000
0!
0&
b0000 $
b0000 )
b1000 #
b1000 (
#2730000
1&
b00100000 %
1!
#2740000
0&
0!
b1001 #
b1001 (
b0010 )
b0010 $
#2750000
1!
b00110010 %
1&
#2760000
0!
0&
b0100 )
b0100 $
b1010 (
b1010 #
#2770000
1&
b01001000 %
1!
#2780000
0&
0!
b1011 (
b1011 #
b0110 $
b0110 )
#2790000
1!
b01100010 %
1&
#2800000
0!
0&
b1000 $
b1000 )
b1100 #
b1100 (
#2810000
1&
b00000000 %
1!
#2820000
0&
0!
b1101 #
b1101 (
b1010 )
b1010 $
#2830000
1!
b00010010 %
1&
#2840000
0!
0&
b1100 )
b1100 $
b1110 (
b1110 #
#2850000
1&
b00101000 %
1!
#2860000
0&
0!
b1111 (
b1111 #
b1110 $
b1110 )
#2870000
1!
b01000010 %
1&
#2880000
0!
0&
b0000 $
b0000 )
b0000 #
b0000 (
#2890000
1&
b01100000 %
1!
#2900000
0&
0!
b0001 #
b0001 (
b0010 )
b0010 $
#2910000
1!
b10000010 %
1&
#2920000
0!
0&
b0100 )
b0100 $
b0010 (
b0010 #
#2930000
1&
b10101000 %
1!
#2940000
0&
0!
b0011 (
b0011 #
b0110 $
b0110 )
#2950000
1!
b11010010 %
1&
#2960000
0!
0&
b1000 $
b1000 )
b0100 #
b0100 (
#2970000
1&
b00000000 %
1!
#2980000
0&
0!
b0101 #
b0101 (
b1010 )
b1010 $
#2990000
1!
b00000010 %
1&
#3000000
0!
0&
b1100 )
b1100 $
b0110 (
b0110 #
#3010000
1&
b00001000 %
1!
#3020000
0&
0!
b0111 (
b0111 #
b1110 $
b1110 )
#3030000
1!
b00010010 %
1&
#3040000
0!
0&
b0000 $
b0000 )
b1000 #
b1000 (
#3050000
1&
b00100000 %
1!
#3060000
0&
0!
b1001 #
b1001 (
b0010 )
b0010 $
#3070000
1!
b00110010 %
1&
#3080000
0!
0&
b0100 )
b0100 $
b1010 (
b1010 #
#3090000
1&
b01001000 %
1!
#3100000
0&
0!
b1011 (
b1011 #
b0110 $
b0110 )
#3110000
1!
b01100010 %
1&
#3120000
0!
0&
b1000 $
b1000 )
b1100 #
b1100 (
#3130000
1&
b00000000 %
1!
#3140000
0&
0!
b1101 #
b1101 (
b1010 )
b1010 $
#3150000
1!
b00010010 %
1&
#3160000
0!
0&
b1100 )
b1100 $
b1110 (
b1110 #
#3170000
1&
b00101000 %
1!
#3180000
0&
0!
b1111 (
b1111 #
b1110 $
b1110 )
#3190000
1!
b01000010 %
1&
#3200000
0!
0&
b0000 $
b0000 )
b0000 #
b0000 (
#3210000
1&
b01100000 %
1!
#3220000
0&
0!
b0001 #
b0001 (
b0010 )
b0010 $
#3230000
1!
b10000010 %
1&
#3240000
0!
0&
b0100 )
b0100 $
b0010 (
b0010 #
#3250000
1&
b10101000 %
1!
#3260000
0&
0!
b0011 (
b0011 #
b0110 $
b0110 )
#3270000
1!
b11010010 %
1&
#3280000
0!
0&
b1000 $
b1000 )
b0100 #
b0100 (
#3290000
1&
b00000000 %
1!
#3300000
0&
0!
b0101 #
b0101 (
b1010 )
b1010 $
#3310000
1!
b00000010 %
1&
#3320000
0!
0&
b1100 )
b1100 $
b0110 (
b0110 #
#3330000
1&
b00001000 %
1!
#3340000
0&
0!
b0111 (
b0111 #
b1110 $
b1110 )
#3350000
1!
b00010010 %
1&
#3360000
0!
0&
b0000 $
b0000 )
b1000 #
b1000 (
#3370000
1&
b00100000 %
1!
#3380000
0&
0!
b1001 #
b1001 (
b0010 )
b0010 $
#3390000
1!
b00110010 %
1&
#3400000
0!
0&
b0100 )
b0100 $
b1010 (
b1010 #
#3410000
1&
b01001000 %
1!
#3420000
0&
0!
b1011 (
b1011 #
b0110 $
b0110 )
#3430000
1!
b01100010 %
1&
#3440000
0!
0&
b1000 $
b1000 )
b1100 #
b1100 (
#3450000
1&
b00000000 %
1!
#3460000
0&
0!
b1101 #
b1101 (
b1010 )
b1010 $
#3470000
1!
b00010010 %
1&
#3480000
0!
0&
b1100 )
b1100 $
b1110 (
b1110 #
#3490000
1&
b00101000 %
1!
#3500000
0&
0!
b1111 (
b1111 #
b1110 $
b1110 )
#3510000
1!
b01000010 %
1&
#3520000
0!
0&
b0000 $
b0000 )
b0000 #
b0000 (
#3530000
1&
b01100000 %
1!
#3540000
0&
0!
b0001 #
b0001 (
b0010 )
b0010 $
#3550000
1!
b10000010 %
1&
#3560000
0!
0&
b0100 )
b0100 $
b0010 (
b0010 #
#3570000
1&
b10101000 %
1!
#3580000
0&
0!
b0011 (
b0011 #
b0110 $
b0110 )
#3590000
1!
b11010010 %
1&
#3600000
0!
0&
b1000 $
b1000 )
b0100 #
b0100 (
#3610000
1&
b00000000 %
1!
#3620000
0&
0!
b0101 #
b0101 (
b1010 )
b1010 $
#3630000
1!
b00000010 %
1&
#3640000
0!
0&
b1100 )
b1100 $
b0110 (
b0110 #
#3650000
1&
b00001000 %
1!
#3660000
0&
0!
b0111 (
b0111 #
b1110 $
b1110 )
#3670000
1!
b00010010 %
1&
#3680000
0!
0&
b0000 $
b0000 )
b1000 #
b1000 (
#3690000
1&
b00100000 %
1!
#3700000
0&
0!
b1001 #
b1001 (
b0010 )
b0010 $
#3710000
1!
b00110010 %
1&
#3720000
0!
0&
b0100 )
b0100 $
b1010 (
b1010 #
#3730000
1&
b01001000 %
1!
#3740000
0&
0!
b1011 (
b1011 #
b0110 $
b0110 )
#3750000
1!
b01100010 %
1&
#3760000
0!
0&
b1000 $
b1000 )
b1100 #
b1100 (
#3770000
1&
b00000000 %
1!
#3780000
0&
0!
b1101 #
b1101 (
b1010 )
b1010 $
#3790000
1!
b00010010 %
1&
#3800000
0!
0&
b1100 )
b1100 $
b1110 (
b1110 #
#3810000
1&
b00101000 %
1!
#3820000
0&
0!
b1111 (
b1111 #
b1110 $
b1110 )
#3830000
1!
b01000010 %
1&
#3840000
0!
0&
b0000 $
b0000 )
b0000 #
b0000 (
#3850000
1&
b01100000 %
1!
#3860000
0&
0!
b0001 #
b0001 (
b0010 )
b0010 $
#3870000
1!
b10000010 %
1&
#3880000
0!
0&
b0100 )
b0100 $
b0010 (
b0010 #
#3890000
1&
b10101000 %
1!
#3900000
0&
0!
b0011 (
b0011 #
b0110 $
b0110 )
#3910000
1!
b11010010 %
1&
#3920000
0!
0&
b1000 $
b1000 )
b0100 #
b0100 (
#3930000
1&
b00000000 %
1!
#3940000
0&
0!
b0101 #
b0101 (
b1010 )
b1010 $
#3950000
1!
b00000010 %
1&
#3960000
0!
0&
b1100 )
b1100 $
b0110 (
b0110 #
#3970000
1&
b00001000 %
1!
#3980000
0&
0!
b0111 (
b0111 #
b1110 $
b1110 )
#3990000
1!
b00010010 %
1&
#4000000
0!
0&
b0000 $
b0000 )
b1000 #
b1000 (
#4010000
1&
b00100000 %
1!
#4020000
0&
0!
b1001 #
b1001 (
b0010 )
b0010 $
#4030000
1!
b00110010 %
1&
#4040000
0!
0&
b0100 )
b0100 $
b1010 (
b1010 #
#4050000
1&
b01001000 %
1!
#4060000
0&
0!
b1011 (
b1011 #
b0110 $
b0110 )
#4070000
1!
b01100010 %
1&
#4080000
0!
0&
b1000 $
b1000 )
b1100 #
b1100 (
#4090000
1&
b00000000 %
1!
#4100000
0&
0!
b1101 #
b1101 (
b1010 )
b1010 $
#4110000
1!
b00010010 %
1&
#4120000
0!
0&
b1100 )
b1100 $
b1110 (
b1110 #
#4130000
1&
b00101000 %
1!
#4140000
0&
0!
b1111 (
b1111 #
b1110 $
b1110 )
#4150000
1!
b01000010 %
1&
#4160000
0!
0&
b0000 $
b0000 )
b0000 #
b0000 (
#4170000
1&
b01100000 %
1!
#4180000
0&
0!
b0001 #
b0001 (
b0010 )
b0010 $
#4190000
1!
b10000010 %
1&
#4200000
0!
0&
b0100 )
b0100 $
b0010 (
b0010 #
#4210000
1&
b10101000 %
1!
#4220000
0&
0!
b0011 (
b0011 #
b0110 $
b0110 )
#4230000
1!
b11010010 %
1&
#4240000
0!
0&
b1000 $
b1000 )
b0100 #
b0100 (
#4250000
1&
b00000000 %
1!
#4260000
0&
0!
b0101 #
b0101 (
b1010 )
b1010 $
#4270000
1!
b00000010 %
1&
#4280000
0!
0&
b1100 )
b1100 $
b0110 (
b0110 #
#4290000
1&
b00001000 %
1!
#4300000
0&
0!
b0111 (
b0111 #
b1110 $
b1110 )
#4310000
1!
b00010010 %
1&
#4320000
0!
0&
b0000 $
b0000 )
b1000 #
b1000 (
#4330000
1&
b00100000 %
1!
#4340000
0&
0!
b1001 #
b1001 (
b0010 )
b0010 $
#4350000
1!
b00110010 %
1&
#4360000
0!
0&
b0100 )
b0100 $
b1010 (
b1010 #
#4370000
1&
b01001000 %
1!
#4380000
0&
0!
b1011 (
b1011 #
b0110 $
b0110 )
#4390000
1!
b01100010 %
1&
#4400000
0!
0&
b1000 $
b1000 )
b1100 #
b1100 (
#4410000
1&
b00000000 %
1!
#4420000
0&
0!
b1101 #
b1101 (
b1010 )
b1010 $
#4430000
1!
b00010010 %
1&
#4440000
0!
0&
b1100 )
b1100 $
b1110 (
b1110 #
#4450000
1&
b00101000 %
1!
#4460000
0&
0!
b1111 (
b1111 #
b1110 $
b1110 )
#4470000
1!
b01000010 %
1&
#4480000
0!
0&
b0000 $
b0000 )
b0000 #
b0000 (
#4490000
1&
b01100000 %
1!
#4500000
0&
0!
b0001 #
b0001 (
b0010 )
b0010 $
#4510000
1!
b10000010 %
1&
#4520000
0!
0&
b0100 )
b0100 $
b0010 (
b0010 #
#4530000
1&
b10101000 %
1!
#4540000
0&
0!
b0011 (
b0011 #
b0110 $
b0110 )
#4550000
1!
b11010010 %
1&
#4560000
0!
0&
b1000 $
b1000 )
b0100 #
b0100 (
#4570000
1&
b00000000 %
1!
#4580000
0&
0!
b0101 #
b0101 (
b1010 )
b1010 $
#4590000
1!
b00000010 %
1&
#4600000
0!
0&
b1100 )
b1100 $
b0110 (
b0110 #
#4610000
1&
b00001000 %
1!
#4620000
0&
0!
b0111 (
b0111 #
b1110 $
b1110 )
#4630000
1!
b00010010 %
1&
#4640000
0!
0&
b0000 $
b0000 )
b1000 #
b1000 (
#4650000
1&
b00100000 %
1!
#4660000
0&
0!
b1001 #
b1001 (
b0010 )
b0010 $
#4670000
1!
b00110010 %
1&
#4680000
0!
0&
b0100 )
b0100 $
b1010 (
b1010 #
#4690000
1&
b01001000 %
1!
#4700000
0&
0!
b1011 (
b1011 #
b0110 $
b0110 )
#4710000
1!
b01100010 %
1&
#4720000
0!
0&
b1000 $
b1000 )
b1100 #
b1100 (
#4730000
1&
b00000000 %
1!
#4740000
0&
0!
b1101 #
b1101 (
b1010 )
b1010 $
#4750000
1!
b00010010 %
1&
#4760000
0!
0&
b1100 )
b1100 $
b1110 (
b1110 #
#4770000
1&
b00101000 %
1!
#4780000
0&
0!
b1111 (
b1111 #
b1110 $
b1110 )
#4790000
1!
b01000010 %
1&
#4800000
0!
0&
b0000 $
b0000 )
b0000 #
b0000 (
#4810000
1&
b01100000 %
1!
#4820000
0&
0!
b0001 #
b0001 (
b0010 )
b0010 $
#4830000
1!
b10000010 %
1&
#4840000
0!
0&
b0100 )
b0100 $
b0010 (
b0010 #
#4850000
1&
b10101000 %
1!
#4860000
0&
0!
b0011 (
b0011 #
b0110 $
b0110 )
#4870000
1!
b11010010 %
1&
#4880000
0!
0&
b1000 $
b1000 )
b0100 #
b0100 (
#4890000
1&
b00000000 %
1!
#4900000
0&
0!
b0101 #
b0101 (
b1010 )
b1010 $
#4910000
1!
b00000010 %
1&
#4920000
0!
0&
b1100 )
b1100 $
b0110 (
b0110 #
#4930000
1&
b00001000 %
1!
#4940000
0&
0!
b0111 (
b0111 #
b1110 $
b1110 )
#4950000
1!
b00010010 %
1&
#4960000
0!
0&
b0000 $
b0000 )
b1000 #
b1000 (
#4970000
1&
b00100000 %
1!
#4980000
0&
0!
b1001 #
b1001 (
b0010 )
b0010 $
#4990000
1!
b00110010 %
1&
#5000000
0!
0&
b0100 )
b0100 $
b1010 (
b1010 #
#5010000
1&
b01001000 %
1!
#5020000
0&
0!
b1011 (
b1011 #
b0110 $
b0110 )
#5030000
1!
b01100010 %
1&
#5040000
0!
0&
b1000 $
b1000 )
b1100 #
b1100 (
#5050000
1&
b00000000 %
1!
#5060000
0&
0!
b1101 #
b1101 (
b1010 )
b1010 $
#5070000
1!
b00010010 %
1&
#5080000
0!
0&
b1100 )
b1100 $
b1110 (
b1110 #
#5090000
1&
b00101000 %
1!
#5100000
0&
0!
b1111 (
b1111 #
b1110 $
b1110 )
#5110000
1!
b01000010 %
1&
#5120000
0!
0&
b0000 $
b0000 )
b0000 #
b0000 (
#5130000
1&
b01100000 %
1!
#5140000
0&
0!
b0001 #
b0001 (
b0010 )
b0010 $
#5150000
1!
b10000010 %
1&
